setup.py
django_modelhistory.egg-info/PKG-INFO
django_modelhistory.egg-info/SOURCES.txt
django_modelhistory.egg-info/dependency_links.txt
django_modelhistory.egg-info/not-zip-safe
django_modelhistory.egg-info/top_level.txt
modelhistory/__init__.py
modelhistory/models.py
modelhistory/tests/__init__.py
modelhistory/tests/forms.py
modelhistory/tests/models.py
modelhistory/tests/runtests.py
modelhistory/tests/tests.py