Metadata-Version: 1.0
Name: django-modelhistory
Version: 0.0.2
Summary: django-modelhistory reusable application for loggin models changes.
Home-page: https://github.com/xando/django-modelhistory
Author: Sebastian Pawluś
Author-email: sebastian.pawlus@gmail.com
License: UNKNOWN
Platform: UNKNOWN
Classifier: Development Status :: 2 - Pre-Alpha
Classifier: Environment :: Web Environment
Classifier: Intended Audience :: Developers
Classifier: License :: OSI Approved :: BSD License
Classifier: Operating System :: OS Independent
Classifier: Programming Language :: Python
Classifier: Framework :: Django
